ot_grn/__init__.py
ot_grn/double_ot.py
ot_grn/evaluate_grn_accuracy.py
ot_grn/extract_top_edges.py
ot_grn/generate_simulated_data.py
ot_grn/load_gastric_cancer_data.py
ot_grn/data/__init__.py
ot_grn/data/normal_data_source1.csv
ot_grn/data/normal_data_source2.csv
ot_grn/data/tumor_data_source1.csv
ot_grn-1.0.1.dist-info/LICENSE
ot_grn-1.0.1.dist-info/METADATA
ot_grn-1.0.1.dist-info/WHEEL
ot_grn-1.0.1.dist-info/top_level.txt
ot_grn-1.0.1.dist-info/RECORD
