Metadata-Version: 2.1
Name: ot-grn
Version: 1.0.1
Summary: Double Optimal Transport for Differential Gene Regulatory Network Inference with Unpaired Samples
Home-page: https://github.com/Mengyu8042/ot-grn
Author: Mengyu Li
Author-email: limengyu516@ruc.edu.cn
License: MIT
Classifier: Programming Language :: Python :: 3
Classifier: License :: OSI Approved :: MIT License
Classifier: Operating System :: OS Independent
Classifier: Intended Audience :: Science/Research
Classifier: Topic :: Scientific/Engineering :: Bio-Informatics
Requires-Python: >=3.7
License-File: LICENSE
Requires-Dist: numpy
Requires-Dist: scipy
Requires-Dist: pandas
Requires-Dist: scikit-learn
Requires-Dist: pot
Provides-Extra: dev
Requires-Dist: pytest; extra == "dev"
Requires-Dist: flake8; extra == "dev"
Requires-Dist: black; extra == "dev"
